{
  "project_info": {
    "project_number": "160682219223",
    "firebase_url": "https://cscb07s26g5-default-rtdb.firebaseio.com",
    "project_id": "cscb07s26g5",
    "storage_bucket": "cscb07s26g5.firebasestorage.app"
  },
  "client": [
    {
      "client_info": {
        "mobilesdk_app_id": "1:160682219223:android:fe29299d2e01b821c80292",
        "android_client_info": {
          "package_name": "com.example.s26g5"
        }
      },
      "oauth_client": [],
      "api_key": [
        {
          "current_key": "AIzaSyDD4SOyGwzf7EqlttpTtlDq_SqcMFzd5lY"
        }
      ],
      "services": {
        "appinvite_service": {
          "other_platform_oauth_client": []
        }
      }
    }
  ],
  "configuration_version": "1"
}